odoo/addons/web_boolean_button/README.rst
odoo/addons/web_boolean_button/__init__.py
odoo/addons/web_boolean_button/__manifest__.py
odoo/addons/web_boolean_button/i18n/web_boolean_button.pot
odoo/addons/web_boolean_button/readme/CONTRIBUTORS.rst
odoo/addons/web_boolean_button/readme/DESCRIPTION.rst
odoo/addons/web_boolean_button/readme/ROADMAP.rst
odoo/addons/web_boolean_button/readme/USAGE.rst
odoo/addons/web_boolean_button/static/description/icon.png
odoo/addons/web_boolean_button/static/description/index.html
odoo/addons/web_boolean_button/static/src/js/basic_fields.js
odoo/addons/web_boolean_button/static/tests/form_tests.js
odoo/addons/web_boolean_button/views/templates.xml
odoo13_addon_web_boolean_button-13.0.1.0.1.dev4.dist-info/METADATA
odoo13_addon_web_boolean_button-13.0.1.0.1.dev4.dist-info/WHEEL
odoo13_addon_web_boolean_button-13.0.1.0.1.dev4.dist-info/top_level.txt
odoo13_addon_web_boolean_button-13.0.1.0.1.dev4.dist-info/RECORD
